LICENSE
MANIFEST.in
README.rst
setup.py
cyhll/__init__.py
cyhll/consts.py
cyhll/hyperloglog.c
cyhll/hyperloglog.pyx
cyhll/murmer3.c
cyhll/murmer3.pxd
cyhll/murmer3.pyx
cyhll.egg-info/PKG-INFO
cyhll.egg-info/SOURCES.txt
cyhll.egg-info/dependency_links.txt
cyhll.egg-info/not-zip-safe
cyhll.egg-info/requires.txt
cyhll.egg-info/top_level.txt
tests/__init__.py
tests/test_hll.py
tests/test_murmer.py